{
    "people": [
        {
            "id": 1,
            "name": "Santoso Nina",
            "photouser":"https://images.unsplash.com/photo-1601412436009-d964bd02edbc?ixlib=rb-4.0.3&ixid=M3wxMjA3fDB8MHxwaG90by1wYWdlfHx8fGVufDB8fHx8fA%3D%3D&auto=format&fit=crop&w=464&q=80",
            "posts": [
              {
                  "id": 1000,
                  "background": "#84767e",
                  "fontbackground": "#fff",
                  "date": "30-07-2023",
                  "fav" : 3,
                  "ciap": "Just had the most delicious ice cream sundae. Sugar rush, here I come! #SweetTooth #IceCreamLover",
                  "loved": true,
                  "thumbhs": "https://picsum.photos/200",
                  "likes": 2222,
                  "respeech": 678,
                  "comments": 90,
                  "responses": [
                    {
                        "id": 1000001,
                        "resname": "Aan Pranowo",
                        "resdate": "30-07-2023",
                        "resfav" : 3,
                        "resciap": "Yeah its delicious ice cream ",
                        "resloved": true,
                        "resthumbhs": "https://picsum.photos/200",
                        "reslikes": 2,
                        "resrespeech": 0,
                        "rescomments": 0
                    },
                    {
                        "id": 1000002,
                        "resname": "Aan Pranowo",
                        "resdate": "30-07-2023",
                        "resfav" : 3,
                        "resciap": "Yeah its delicious ice cream ",
                        "resloved": true,
                        "resthumbhs": "https://picsum.photos/200",
                        "reslikes": 2,
                        "resrespeech": 0,
                        "rescomments": 0
                    },
                    {
                        "id": 1000003,
                        "resname": "Aan Pranowo",
                        "resdate": "30-07-2023",
                        "resfav" : 3,
                        "resciap": "Yeah its delicious ice cream ",
                        "resloved": true,
                        "resthumbhs": "https://picsum.photos/200",
                        "reslikes": 2,
                        "resrespeech": 0,
                        "rescomments": 0
                    }
                ]
              },
              {
                  "id": 1001,
                  "background": "#03ad8e",
                  "fontbackground": "#fff",
                  "date": "01-07-2023",
                  "fav" : 3,
                  "ciap": "Started a new fitness challenge today. Pushing my limits and striving for progress. #FitnessGoals #ChallengeAccepted",
                  "loved": true,
                  "thumbhs": "https://picsum.photos/200",
                  "likes": 231,
                  "respeech": 88,
                  "comments": 12,
                  "responses": [
                    {
                        "id": 1001001,
                        "resname": "Aan Pranowo",
                        "resdate": "30-07-2023",
                        "resfav" : 3,
                        "resciap": "Yeah its delicious ice cream ",
                        "resloved": true,
                        "resthumbhs": "https://picsum.photos/200",
                        "reslikes": 2,
                        "resrespeech": 0,
                        "rescomments": 0
                    },
                    {
                        "id": 1001002,
                        "resname": "Aan Pranowo",
                        "resdate": "30-07-2023",
                        "resfav" : 3,
                        "resciap": "Yeah its delicious ice cream ",
                        "resloved": true,
                        "resthumbhs": "https://picsum.photos/200",
                        "reslikes": 2,
                        "resrespeech": 0,
                        "rescomments": 0
                    },
                    {
                        "id": 1001003,
                        "resname": "Aan Pranowo",
                        "resdate": "30-07-2023",
                        "resfav" : 3,
                        "resciap": "Yeah its delicious ice cream ",
                        "resloved": true,
                        "resthumbhs": "https://picsum.photos/200",
                        "reslikes": 2,
                        "resrespeech": 0,
                        "rescomments": 0
                    },{
                        "id": 1001004,
                        "resname": "Ian Santoso",
                        "resdate": "30-07-2023",
                        "resfav" : 3,
                        "resciap": "Yeah its delicious ice cream ",
                        "resloved": true,
                        "resthumbhs": "https://picsum.photos/200",
                        "reslikes": 2,
                        "resrespeech": 0,
                        "rescomments": 0
                    },{
                        "id": 1001005,
                        "resname": "Bambank",
                        "resdate": "30-07-2023",
                        "resfav" : 3,
                        "resciap": "Yeah its delicious ice cream ",
                        "resloved": true,
                        "resthumbhs": "https://picsum.photos/200",
                        "reslikes": 2,
                        "resrespeech": 0,
                        "rescomments": 0
                    },{
                        "id": 1001006,
                        "resname": "Trimbel",
                        "resdate": "30-07-2023",
                        "resfav" : 3,
                        "resciap": "Yeah its delicious ice cream ",
                        "resloved": true,
                        "resthumbhs": "https://picsum.photos/200",
                        "reslikes": 2,
                        "resrespeech": 0,
                        "rescomments": 0
                    }
                ]
              }
            ]
        },
        {
            "id": 2,
            "name": "Deandra",
            "photouser":"https://images.unsplash.com/photo-1580489944761-15a19d654956?ixlib=rb-4.0.3&ixid=M3wxMjA3fDB8MHxwaG90by1wYWdlfHx8fGVufDB8fHx8fA%3D%3D&auto=format&fit=crop&w=461&q=80",
            "posts": [
              {
                  "id": 2000,
                  "background": "#afc906",
                  "fontbackground": "#fff",
                  "date": "12-07-2023",
                  "fav" : 3,
                  "ciap": "Rediscovered my love for painting after a long break. Feels amazing to express myself through art. #CreativeOutlet #ArtisticSoul",
                  "loved": true,
                  "thumbhs": "https://picsum.photos/200",
                  "likes": 12,
                  "respeech": 7,
                  "comments": 6,
                  "responses": [
                    {
                        "id": 1000001,
                        "resname": "Aan Pranowo",
                        "resdate": "30-07-2023",
                        "resfav" : 3,
                        "resciap": "Yeah its delicious ice cream ",
                        "resloved": true,
                        "resthumbhs": "https://picsum.photos/200",
                        "reslikes": 2,
                        "resrespeech": 0,
                        "rescomments": 0
                    },
                    {
                        "id": 1000002,
                        "resname": "Aan Pranowo",
                        "resdate": "30-07-2023",
                        "resfav" : 3,
                        "resciap": "Yeah its delicious ice cream ",
                        "resloved": true,
                        "resthumbhs": "https://picsum.photos/200",
                        "reslikes": 2,
                        "resrespeech": 0,
                        "rescomments": 0
                    },
                    {
                        "id": 1000003,
                        "resname": "Aan Pranowo",
                        "resdate": "30-07-2023",
                        "resfav" : 3,
                        "resciap": "Yeah its delicious ice cream ",
                        "resloved": true,
                        "resthumbhs": "https://picsum.photos/200",
                        "reslikes": 2,
                        "resrespeech": 0,
                        "rescomments": 0
                    }
                ]
              },
              {
                  "id": 2001,
                  "background": "#70d32a",
                  "fontbackground": "#fff",
                  "date": "11-07-2023",
                  "fav" : 3,
                  "ciap": "Life is too short to hold grudges. Letting go of negativity and embracing forgiveness. #LettingGo #Positivity",
                  "loved": true,
                  "thumbhs": "https://picsum.photos/200",
                  "likes": 5555,
                  "respeech": 200,
                  "comments": 21,"responses": [
                    {
                        "id": 1000001,
                        "resname": "Aan Pranowo",
                        "resdate": "30-07-2023",
                        "resfav" : 3,
                        "resciap": "Yeah its delicious ice cream ",
                        "resloved": true,
                        "resthumbhs": "https://picsum.photos/200",
                        "reslikes": 2,
                        "resrespeech": 0,
                        "rescomments": 0
                    },
                    {
                        "id": 1000002,
                        "resname": "Aan Pranowo",
                        "resdate": "30-07-2023",
                        "resfav" : 3,
                        "resciap": "Yeah its delicious ice cream ",
                        "resloved": true,
                        "resthumbhs": "https://picsum.photos/200",
                        "reslikes": 2,
                        "resrespeech": 0,
                        "rescomments": 0
                    },
                    {
                        "id": 1000003,
                        "resname": "Aan Pranowo",
                        "resdate": "30-07-2023",
                        "resfav" : 3,
                        "resciap": "Yeah its delicious ice cream ",
                        "resloved": true,
                        "resthumbhs": "https://picsum.photos/200",
                        "reslikes": 2,
                        "resrespeech": 0,
                        "rescomments": 0
                    }
                ]
              }
            ]
        },{
            "id": 3,
            "name": "Sophia Anderson",
            "photouser":"https://images.unsplash.com/photo-1509967419530-da38b4704bc6?ixlib=rb-4.0.3&ixid=M3wxMjA3fDB8MHxwaG90by1wYWdlfHx8fGVufDB8fHx8fA%3D%3D&auto=format&fit=crop&w=895&q=80",
            "posts": [
              {
                  "id": 3000,
                  "background": "#845EC2",
                  "fontbackground": "#fff",
                  "date": "02-07-2023",
                  "fav" : 3,
                  "ciap": "Spent the whole afternoon exploring a new hiking trail. The views were absolutely breathtaking! #NatureAdventure #Hiking",
                  "loved": true,
                  "thumbhs": "https://picsum.photos/200",
                  "likes": 6234,
                  "respeech": 4124,
                  "comments": 77,
                  "responses": [
                    {
                        "id": 1000001,
                        "resname": "Aan Pranowo",
                        "resdate": "30-07-2023",
                        "resfav" : 3,
                        "resciap": "Yeah its delicious ice cream ",
                        "resloved": true,
                        "resthumbhs": "https://picsum.photos/200",
                        "reslikes": 2,
                        "resrespeech": 0,
                        "rescomments": 0
                    },
                    {
                        "id": 1000002,
                        "resname": "Aan Pranowo",
                        "resdate": "30-07-2023",
                        "resfav" : 3,
                        "resciap": "Yeah its delicious ice cream ",
                        "resloved": true,
                        "resthumbhs": "https://picsum.photos/200",
                        "reslikes": 2,
                        "resrespeech": 0,
                        "rescomments": 0
                    },
                    {
                        "id": 1000003,
                        "resname": "Aan Pranowo",
                        "resdate": "30-07-2023",
                        "resfav" : 3,
                        "resciap": "Yeah its delicious ice cream ",
                        "resloved": true,
                        "resthumbhs": "https://picsum.photos/200",
                        "reslikes": 2,
                        "resrespeech": 0,
                        "rescomments": 0
                    }
                ]
              },
              {
                  "id": 3001,
                  "background": "#D65DB1",
                  "fontbackground": "#fff",
                  "date": "09-07-2023",
                  "fav" : 3,
                  "ciap": "Can't believe it's already July! Time is flying by so quickly. #TimeFlies #July",
                  "loved": true,
                  "thumbhs": "https://picsum.photos/200",
                  "likes": 127,
                  "respeech": 15,
                  "comments": 67,
                  "responses": [
                    {
                        "id": 1000001,
                        "resname": "Aan Pranowo",
                        "resdate": "30-07-2023",
                        "resfav" : 3,
                        "resciap": "Yeah its delicious ice cream ",
                        "resloved": true,
                        "resthumbhs": "https://picsum.photos/200",
                        "reslikes": 2,
                        "resrespeech": 0,
                        "rescomments": 0
                    },
                    {
                        "id": 1000002,
                        "resname": "Aan Pranowo",
                        "resdate": "30-07-2023",
                        "resfav" : 3,
                        "resciap": "Yeah its delicious ice cream ",
                        "resloved": true,
                        "resthumbhs": "https://picsum.photos/200",
                        "reslikes": 2,
                        "resrespeech": 0,
                        "rescomments": 0
                    },
                    {
                        "id": 1000003,
                        "resname": "Aan Pranowo",
                        "resdate": "30-07-2023",
                        "resfav" : 3,
                        "resciap": "Yeah its delicious ice cream ",
                        "resloved": true,
                        "resthumbhs": "https://picsum.photos/200",
                        "reslikes": 2,
                        "resrespeech": 0,
                        "rescomments": 0
                    }
                ]
              }
            ]
        },{
            "id": 4,
            "name": "Liam Thompson",
            "photouser":"https://images.unsplash.com/photo-1616766098946-e4fabb7d6da0?ixlib=rb-4.0.3&ixid=M3wxMjA3fDB8MHxwaG90by1wYWdlfHx8fGVufDB8fHx8fA%3D%3D&auto=format&fit=crop&w=387&q=80",
            "posts": [
              {
                  "id": 4000,
                  "background": "#FF6F91",
                  "fontbackground": "#fff",
                  "date": "14-07-2023",
                  "fav" : 3,
                  "ciap": "Tried a new hobby today, and it's so much fun! Excited to dive deeper into it. #NewAdventure #HobbyTime",
                  "loved": true,
                  "thumbhs": "https://picsum.photos/200",
                  "likes": 19,
                  "respeech": 22,
                  "comments": 16,
                  "responses": [
                    {
                        "id": 1000001,
                        "resname": "Aan Pranowo",
                        "resdate": "30-07-2023",
                        "resfav" : 3,
                        "resciap": "Yeah its delicious ice cream ",
                        "resloved": true,
                        "resthumbhs": "https://picsum.photos/200",
                        "reslikes": 2,
                        "resrespeech": 0,
                        "rescomments": 0
                    },
                    {
                        "id": 1000002,
                        "resname": "Aan Pranowo",
                        "resdate": "30-07-2023",
                        "resfav" : 3,
                        "resciap": "Yeah its delicious ice cream ",
                        "resloved": true,
                        "resthumbhs": "https://picsum.photos/200",
                        "reslikes": 2,
                        "resrespeech": 0,
                        "rescomments": 0
                    },
                    {
                        "id": 1000003,
                        "resname": "Aan Pranowo",
                        "resdate": "30-07-2023",
                        "resfav" : 3,
                        "resciap": "Yeah its delicious ice cream ",
                        "resloved": true,
                        "resthumbhs": "https://picsum.photos/200",
                        "reslikes": 2,
                        "resrespeech": 0,
                        "rescomments": 0
                    }
                ]
              },
              {
                  "id": 4001,
                  "background": "#FF9671",
                  "fontbackground": "#fff",
                  "date": "11-07-2023",
                  "fav" : 6,
                  "ciap": "Just adopted the most adorable puppy. Can't wait for all the adventures we'll have together! #NewPuppy #FurBaby",
                  "loved": true,
                  "thumbhs": "https://picsum.photos/200",
                  "likes": 156,
                  "respeech": 1,
                  "comments": 2,
                  "responses": [
                    {
                        "id": 1000001,
                        "resname": "Aan Pranowo",
                        "resdate": "30-07-2023",
                        "resfav" : 3,
                        "resciap": "Yeah its delicious ice cream ",
                        "resloved": true,
                        "resthumbhs": "https://picsum.photos/200",
                        "reslikes": 2,
                        "resrespeech": 0,
                        "rescomments": 0
                    },
                    {
                        "id": 1000002,
                        "resname": "Aan Pranowo",
                        "resdate": "30-07-2023",
                        "resfav" : 3,
                        "resciap": "Yeah its delicious ice cream ",
                        "resloved": true,
                        "resthumbhs": "https://picsum.photos/200",
                        "reslikes": 2,
                        "resrespeech": 0,
                        "rescomments": 0
                    },
                    {
                        "id": 1000003,
                        "resname": "Aan Pranowo",
                        "resdate": "30-07-2023",
                        "resfav" : 3,
                        "resciap": "Yeah its delicious ice cream ",
                        "resloved": true,
                        "resthumbhs": "https://picsum.photos/200",
                        "reslikes": 2,
                        "resrespeech": 0,
                        "rescomments": 0
                    }
                ]
              }
            ]
        },{
            "id": 5,
            "name": "Isabella Ramirez",
            "photouser":"https://images.unsplash.com/photo-1531746020798-e6953c6e8e04?ixlib=rb-4.0.3&ixid=M3wxMjA3fDB8MHxwaG90by1wYWdlfHx8fGVufDB8fHx8fA%3D%3D&auto=format&fit=crop&w=464&q=80",
            "posts": [
              {
                  "id": 5000,
                  "background": "#FFC75F",
                  "fontbackground": "#333",
                  "date": "09-07-2023",
                  "fav" : 3,
                  "ciap": "Spontaneous road trip with friends! Making memories and exploring new places. #RoadTrip #AdventureTime",
                  "loved": true,
                  "thumbhs": "https://picsum.photos/200",
                  "likes": 6765,
                  "respeech": 123,
                  "comments": 34,
                  "responses": [
                    {
                        "id": 1000001,
                        "resname": "Aan Pranowo",
                        "resdate": "30-07-2023",
                        "resfav" : 3,
                        "resciap": "Yeah its delicious ice cream ",
                        "resloved": true,
                        "resthumbhs": "https://picsum.photos/200",
                        "reslikes": 2,
                        "resrespeech": 0,
                        "rescomments": 0
                    },
                    {
                        "id": 1000002,
                        "resname": "Aan Pranowo",
                        "resdate": "30-07-2023",
                        "resfav" : 3,
                        "resciap": "Yeah its delicious ice cream ",
                        "resloved": true,
                        "resthumbhs": "https://picsum.photos/200",
                        "reslikes": 2,
                        "resrespeech": 0,
                        "rescomments": 0
                    },
                    {
                        "id": 1000003,
                        "resname": "Aan Pranowo",
                        "resdate": "30-07-2023",
                        "resfav" : 3,
                        "resciap": "Yeah its delicious ice cream ",
                        "resloved": true,
                        "resthumbhs": "https://picsum.photos/200",
                        "reslikes": 2,
                        "resrespeech": 0,
                        "rescomments": 0
                    }
                ]
              },
              {
                  "id": 5001,
                  "background": "#F9F871",
                  "fontbackground": "#333",
                  "date": "01-07-2023",
                  "fav" : 6,
                  "ciap": "Feeling grateful for all the amazing people in my life who constantly lift me up. #Gratitude #Blessed",
                  "loved": true,
                  "thumbhs": "https://picsum.photos/200",
                  "likes": 5423,
                  "respeech": 678,
                  "comments": 25,
                  "responses": [
                    {
                        "id": 1000001,
                        "resname": "Aan Pranowo",
                        "resdate": "30-07-2023",
                        "resfav" : 3,
                        "resciap": "Yeah its delicious ice cream ",
                        "resloved": true,
                        "resthumbhs": "https://picsum.photos/200",
                        "reslikes": 2,
                        "resrespeech": 0,
                        "rescomments": 0
                    },
                    {
                        "id": 1000002,
                        "resname": "Aan Pranowo",
                        "resdate": "30-07-2023",
                        "resfav" : 3,
                        "resciap": "Yeah its delicious ice cream ",
                        "resloved": true,
                        "resthumbhs": "https://picsum.photos/200",
                        "reslikes": 2,
                        "resrespeech": 0,
                        "rescomments": 0
                    },
                    {
                        "id": 1000003,
                        "resname": "Aan Pranowo",
                        "resdate": "30-07-2023",
                        "resfav" : 3,
                        "resciap": "Yeah its delicious ice cream ",
                        "resloved": true,
                        "resthumbhs": "https://picsum.photos/200",
                        "reslikes": 2,
                        "resrespeech": 0,
                        "rescomments": 0
                    }
                ]
              },
              {
                "id": 5002,
                "background": "#FF0073",
                "fontbackground": "#fff",
                "date": "02-07-2023",
                "fav" : 19,
                "ciap": "Feeling grateful for all the amazing people in my life who constantly lift me up. #Gratitude #Blessed",
                "loved": true,
                "thumbhs": "https://picsum.photos/200",
                "likes": 551,
                "respeech": 123,
                "comments": 44,
                "responses": [
                    {
                        "id": 1000001,
                        "resname": "Aan Pranowo",
                        "resdate": "30-07-2023",
                        "resfav" : 3,
                        "resciap": "Yeah its delicious ice cream ",
                        "resloved": true,
                        "resthumbhs": "https://picsum.photos/200",
                        "reslikes": 2,
                        "resrespeech": 0,
                        "rescomments": 0
                    },
                    {
                        "id": 1000002,
                        "resname": "Aan Pranowo",
                        "resdate": "30-07-2023",
                        "resfav" : 3,
                        "resciap": "Yeah its delicious ice cream ",
                        "resloved": true,
                        "resthumbhs": "https://picsum.photos/200",
                        "reslikes": 2,
                        "resrespeech": 0,
                        "rescomments": 0
                    },
                    {
                        "id": 1000003,
                        "resname": "Aan Pranowo",
                        "resdate": "30-07-2023",
                        "resfav" : 3,
                        "resciap": "Yeah its delicious ice cream ",
                        "resloved": true,
                        "resthumbhs": "https://picsum.photos/200",
                        "reslikes": 2,
                        "resrespeech": 0,
                        "rescomments": 0
                    }
                ]
                }
            ]
        },{
            "id": 6,
            "name": "Ava Lewis",
            "photouser":"https://images.unsplash.com/photo-1544005313-94ddf0286df2?ixlib=rb-4.0.3&ixid=M3wxMjA3fDB8MHxwaG90by1wYWdlfHx8fGVufDB8fHx8fA%3D%3D&auto=format&fit=crop&w=388&q=80",
            "posts": [
              {
                  "id": 6000,
                  "background": "#DC97B3",
                  "fontbackground": "#fff",
                  "date": "09-07-2023",
                  "fav" : 3,
                  "ciap": "A rainy day calls for cozy blankets, hot cocoa, and a good book. #RainyDayVibes #CozyTime",
                  "loved": true,
                  "thumbhs": "https://picsum.photos/200",
                  "likes": 789,
                  "respeech": 200,
                  "comments": 77,
                  "responses": [
                    {
                        "id": 1000001,
                        "resname": "Aan Pranowo",
                        "resdate": "30-07-2023",
                        "resfav" : 3,
                        "resciap": "Yeah its delicious ice cream ",
                        "resloved": true,
                        "resthumbhs": "https://picsum.photos/200",
                        "reslikes": 2,
                        "resrespeech": 0,
                        "rescomments": 0
                    },
                    {
                        "id": 1000002,
                        "resname": "Aan Pranowo",
                        "resdate": "30-07-2023",
                        "resfav" : 3,
                        "resciap": "Yeah its delicious ice cream ",
                        "resloved": true,
                        "resthumbhs": "https://picsum.photos/200",
                        "reslikes": 2,
                        "resrespeech": 0,
                        "rescomments": 0
                    },
                    {
                        "id": 1000003,
                        "resname": "Aan Pranowo",
                        "resdate": "30-07-2023",
                        "resfav" : 3,
                        "resciap": "Yeah its delicious ice cream ",
                        "resloved": true,
                        "resthumbhs": "https://picsum.photos/200",
                        "reslikes": 2,
                        "resrespeech": 0,
                        "rescomments": 0
                    }
                ]
              },
              {
                  "id": 6001,
                  "background": "##5DBAB2",
                  "fontbackground": "#333",
                  "date": "01-07-2023",
                  "fav" : 6,
                  "ciap": "Started learning a new language, and it's both challenging and exciting. #LanguageLearning #Multilingual",
                  "loved": true,
                  "thumbhs": "https://picsum.photos/200",
                  "likes": 45,
                  "respeech": 13,
                  "comments": 45,
                  "responses": [
                    {
                        "id": 1000001,
                        "resname": "Aan Pranowo",
                        "resdate": "30-07-2023",
                        "resfav" : 3,
                        "resciap": "Yeah its delicious ice cream ",
                        "resloved": true,
                        "resthumbhs": "https://picsum.photos/200",
                        "reslikes": 2,
                        "resrespeech": 0,
                        "rescomments": 0
                    },
                    {
                        "id": 1000002,
                        "resname": "Aan Pranowo",
                        "resdate": "30-07-2023",
                        "resfav" : 3,
                        "resciap": "Yeah its delicious ice cream ",
                        "resloved": true,
                        "resthumbhs": "https://picsum.photos/200",
                        "reslikes": 2,
                        "resrespeech": 0,
                        "rescomments": 0
                    },
                    {
                        "id": 1000003,
                        "resname": "Aan Pranowo",
                        "resdate": "30-07-2023",
                        "resfav" : 3,
                        "resciap": "Yeah its delicious ice cream ",
                        "resloved": true,
                        "resthumbhs": "https://picsum.photos/200",
                        "reslikes": 2,
                        "resrespeech": 0,
                        "rescomments": 0
                    }
                ]
              },
              {
                "id": 6002,
                "background": "#49817B",
                "fontbackground": "#fff",
                "date": "02-07-2023",
                "fav" : 19,
                "ciap": "Celebrated a milestone today, and I'm incredibly proud of how far I've come. #AchievementUnlocked #Milestone",
                "loved": true,
                "thumbhs": "https://picsum.photos/200",
                "likes": 67,
                "respeech": 33,
                "comments": 12,
                "responses": [
                    {
                        "id": 1000001,
                        "resname": "Aan Pranowo",
                        "resdate": "30-07-2023",
                        "resfav" : 3,
                        "resciap": "Yeah its delicious ice cream ",
                        "resloved": true,
                        "resthumbhs": "https://picsum.photos/200",
                        "reslikes": 2,
                        "resrespeech": 0,
                        "rescomments": 0
                    },
                    {
                        "id": 1000002,
                        "resname": "Aan Pranowo",
                        "resdate": "30-07-2023",
                        "resfav" : 3,
                        "resciap": "Yeah its delicious ice cream ",
                        "resloved": true,
                        "resthumbhs": "https://picsum.photos/200",
                        "reslikes": 2,
                        "resrespeech": 0,
                        "rescomments": 0
                    },
                    {
                        "id": 1000003,
                        "resname": "Aan Pranowo",
                        "resdate": "30-07-2023",
                        "resfav" : 3,
                        "resciap": "Yeah its delicious ice cream ",
                        "resloved": true,
                        "resthumbhs": "https://picsum.photos/200",
                        "reslikes": 2,
                        "resrespeech": 0,
                        "rescomments": 0
                    }
                ]
                },
               {
                "id": 6003,
                "background": "#9E6E00",
                "fontbackground": "#fff",
                "date": "02-07-2023",
                "fav" : 77,
                "ciap": "Just tried a new restaurant in town, and the food was out of this world! Highly recommend it. #Foodie #FoodLover",
                "loved": true,
                "thumbhs": "https://picsum.photos/200",
                "likes": 56,
                "respeech": 12,
                "comments": 44,
                "responses": [
                    {
                        "id": 1000001,
                        "resname": "Aan Pranowo",
                        "resdate": "30-07-2023",
                        "resfav" : 3,
                        "resciap": "Yeah its delicious ice cream ",
                        "resloved": true,
                        "resthumbhs": "https://picsum.photos/200",
                        "reslikes": 2,
                        "resrespeech": 0,
                        "rescomments": 0
                    },
                    {
                        "id": 1000002,
                        "resname": "Aan Pranowo",
                        "resdate": "30-07-2023",
                        "resfav" : 3,
                        "resciap": "Yeah its delicious ice cream ",
                        "resloved": true,
                        "resthumbhs": "https://picsum.photos/200",
                        "reslikes": 2,
                        "resrespeech": 0,
                        "rescomments": 0
                    },
                    {
                        "id": 1000003,
                        "resname": "Aan Pranowo",
                        "resdate": "30-07-2023",
                        "resfav" : 3,
                        "resciap": "Yeah its delicious ice cream ",
                        "resloved": true,
                        "resthumbhs": "https://picsum.photos/200",
                        "reslikes": 2,
                        "resrespeech": 0,
                        "rescomments": 0
                    }
                ]
                }
            ]
        }
    ]
}
  